tyk_time_converter_server/__init__.py
tyk_time_converter_server/tyk_time_converter_server.py
tyk_time_converter_server-0.1.4.dist-info/licenses/LICENSE
tyk_time_converter_server-0.1.4.dist-info/METADATA
tyk_time_converter_server-0.1.4.dist-info/WHEEL
tyk_time_converter_server-0.1.4.dist-info/entry_points.txt
tyk_time_converter_server-0.1.4.dist-info/top_level.txt
tyk_time_converter_server-0.1.4.dist-info/RECORD
