Metadata-Version: 2.4
Name: tyk_time_converter_server
Version: 0.1.4
Summary: 一个将秒数转换为天、小时、分钟、秒格式的MCP服务
Author-email: tangyongkang <316674908@qq.com>
License: MIT License
Classifier: Programming Language :: Python :: 3
Classifier: License :: OSI Approved :: MIT License
Classifier: Operating System :: OS Independent
Requires-Python: >=3.7
License-File: LICENSE
Requires-Dist: mcp>=0.1.0
Dynamic: license-file
